{
  "ACK Technologies Ltd": [
    "CSTA 212, E-04, E-04C ELT",
    "CSTA 277 E-04/E-4C ELT"
  ],
  "ACR": [
    "CSTA 242, ME406/HM/P/U, ELT",
    "CSTA 317, Artex ELT 345",
    "CSTA 323, Artex ELT 1000 Auto Fixed",
    "CSTA 324, Artex ELT 345 Auto Fixed",
    "CSTA 210, C406-1/C406-1HM ELT",
    "CSTA 210, C406-2/B406-4/C406-2HM/RB406-1HM ELT",
    "CSTA 197, ME406/HM/P/U ELT",
    "CSTA 135, C406-N/N HM ELT",
    "CSTA 84, RLB 28 EPIRB",
    "CSTA 83, RLB 27 EPIRB",
    "CSTA 107, RLB 32 Cat 1 (Serialised non-TAC) EPIRB",
    "CSTA 107, RLB 32 Cat 2 (Serialised non-TAC) EPIRB",
    "CSTA 173, RLB 35 Globalfix EPIRB",
    "CSTA 189, RLB 36-40, Globalfix iPro EPIRB",
    "CSTA 213, RLB 36-40, Globalfix iPro EPIRB",
    "CSTA 234, RLB 36-40 Globalfix iPro EPIRB",
    "CSTA 246, GPS, RLB 36-40 Globalfix iPro EPIRB",
    "CSTA 258, RLB 36-40, Globalfix iPro EPIRB",
    "CSTA 270, EPIRB, Globalfix V4, RLB 41",
    "CSTA 284, RLB 36-40, Globalfix Pro FF EPIRB",
    "CSTA 288, EPIRB, Globalfix V4, RLB 41 EPIRB",
    "CSTA 319, RLB 41 EPIRB (Float Free / non-Float Free)",
    "CSTA 320, RLB 36-40 Float Free EPIRB",
    "CSTA 341 RLB41 GLOBALFIX V4 EPIRB",
    "CSTA 108, RLB 33 Rapidfix GPS EPIRB",
    "CSTA 127, RLB 35 Globalfix EPIRB",
    "CSTA 136, RLB 35 Globalfix EPIRB",
    "CSTA 107, RLB 32 Cat2 EPIRB",
    "CSTA 109, EPIRB RLB 100 ",
    "CSTA 107, RLB 32 Cat 1 EPIRB CSTA coded",
    "CSTA 236 RLB 36-40 Globalfix iPro EPIRB",
    "CSTA 284, RLB 37M, ResQmate EPIRB",
    "CSTA 320, RLB 37M Float Free EPIRB",
    "CSTA 330, Globalfix V4, RLB 41 EPIRB",
    "CSTA 141, RLB 33S, SSAS EPIRB",
    "CSTA 156, Aquafix/Aerofix PLB 200",
    "CSTA 157, Aquafix/Aerofix PLB 201",
    "CSTA 169, PLB 300 GPS",
    "CSTA 174, PLB 200",
    "CSTA 181, ACR PLB 300",
    "CSTA 187, PLB 300",
    "CSTA 190, PLB 300",
    "CSTA 198, Aqualink 350B GPS PLB",
    "CSTA 199, PLB 300",
    "CSTA 207, Aquafix PLB 200",
    "CSTA 208, Aqualink PLB 350B",
    "CSTA 219, PLB 375 ResQLink, GPS",
    "CSTA 224, PLB 375 ResQLink, GPS ",
    "CSTA 228, AquaLink PLB350B PLB",
    "CSTA 233, PLB 375, ResQLink+ ",
    "CSTA 241, PLB 375/ResQLink+",
    "CSTA 245, GPS, PLB 375 ResQLink/+",
    "CSTA 257, ACR, PLB 375 ResQLink, GPS",
    "CSTA 257, PLB 375 ResQLink, GPS",
    "CSTA 265, PLB 375, ResQLink / ResQlink +",
    "CSTA 266, Aqualink PLB 350B",
    "CSTA 271, PLB 375, ResQLink / ResQlink +",
    "CSTA 276, PLB 375, ResQLink / ResQlink +",
    "CSTA 279, PLB 375, ResQLink / ResQlink +",
    "CSTA 287, PLB 375, ResQLink+",
    "CSTA 294, PLB-375 (ResQLink+)",
    "CSTA 305, PLB 375, ResQLink / ResQlink+",
    "CSTA 311, PLB 400",
    "CSTA 314, PLB 375 / 375 (ResQLink+)",
    "CSTA 315, PLB 425",
    "CSTA 316, PLB 400",
    "CSTA 329 ACR PLB 400, ResQLink 400",
    "CSTA 331 ACR PLB 400, ResQLink 400",
    "CSTA 335 ACR PLB 400, ResQLink 400",
    "CSTA 339 ACR PLB 400, ResQLink 400",
    "CSTA 343 ACR PLB 400, ResQLink 400",
    "CSTA 344 ACR PLB 400, ResQLink 400",
    "CSTA 711 SLB-2000-100",
    "CSTA 109, GyPSI PLB-100",
    "CSTA 143, Aquafix/Aerofix PLB",
    "CSTA 144, Aquafix/Aerofix PLB",
    "CSTA 198, PLB 350A GPS",
    "CSTA 198, SARLink PLB 350B",
    "CSTA 198, SARLink View PLB 350C",
    "CSTA 198, Aqualink View PLB 350C ",
    "CSTA 208, Aqualink View PLB 350C",
    "CSTA 228, AquaLink 406, pn 2882 PLB",
    "CSTA 228, PLB 350B Slim/Float pn 2882",
    "CSTA 228, PLB 350C Slim/Float pn 2884",
    "CSTA 228, AquaLink View PLB350C",
    "CSTA 254, PLB 375 ResQLink, GPS",
    "CSTA 266, Aqualink PLB 350C",
    "CSTA 310, Artex PLB",
    "CSTA 315, PLB 400",
    "CSTA 311, PLB 425",
    "CSTA 316, PLB 425",
    "CSTA 333, Artex PLB",
    "CSTA 329 ACR PLB 425, ResQLink View",
    "CSTA 331 ACR PLB 425, ResQLink View",
    "CSTA 335 ACR PLB 425, ResQLink View",
    "CSTA 339 ACR PLB 425, ResQLink View",
    "CSTA 343 ACR PLB 425, ResQLink View",
    "CSTA 344 ACR PLB 425, ResQLink View",
    "CSTA 301, PLB 375, ResQLink / ResQlink+"
  ],
  "ACR (Artex)": [
    "ACR CSTA 267, Artex ELT 345",
    "CSTA 252, C406-N/N HM ELT",
    "CSTA 251, Artex ELT 1000",
    "CSTA 298, Artex ELT 4000",
    "CSTA 342, Artex PLB",
    "CSTA 299, Artex PLB"
  ],
  "Air Precision": ["CSTA 74, ELT 96 / 96S / 97"],
  "Alden Satfind": [
    "CSTA 43, 78, Alden Satfind, non-GPS EPIRB",
    "CSTA 102, Alden S1510 GPS, CSTA 102 EPIRB"
  ],
  "Ameri-King": [
    "CSTA 179, AK-451 non-GPS range ELT",
    "CSTA 179, AK-451 GPS range ELT"
  ],
  "Anritsu": ["CSTA 86, REB 23-01, Anritsu RJ302A EPIRB"],
  "Artex": [
    "CSTA 112, non-GPS C406-2/B406-4/G406-4 ELT",
    "CSTA 170, C406-1 Helicopter ELT",
    "CSTA 170 GPS, C406-2/B406-4/G406-4 ELT",
    "CSTA 112, C406-1 ELT",
    "CSTA 112 GPS C406-2/B406-4/G406-4 ELT",
    "CSTA 67, ELT 110-406",
    "CSTA 126, G406-1 / 2 ELT",
    "CSTA 104, ELT 110-406 NAV ELT",
    "CSTA 152, ME 406 ELT",
    "CSTA 188, ME 406 ELT",
    "CSTA 170 non-GPS, C406-2/B406-4/G406-4 ELT"
  ],
  "Astronics": ["CSTA 133, SRB 406 ELT"],
  "Astronics, DME Corporation": ["CSTA 303, SRB 406G Single Antenna, ELT"],
  "Breitling SA": ["CSTA 717, Breitling watch, PLB"],
  "BriarTek Inc": ["CSTA 325, Orca 406"],
  "Caledonian": ["CSTA 8, CPT-600M EPIRB", "CSTA 33, CPT 600N EPIRB"],
  "Caledonian Airborne Sys Ltd": [
    "CSTA 90, ADELT CPT 609 ELT",
    "CSTA 154, CPT 900 ELT"
  ],
  "CETC Group": ["CSTA 237, VEP8 EPIRB"],
  "Cobham SATCOM": [
    "CSTA 289 Sailor 4065 GNSS (Z702) EPIRB",
    "CSTA 289 Sailor 4065 (Z704) non-GPS EPIRB"
  ],
  "Crewsaver (Orolia)": [
    "CSTA 289 Crewsaver Crewfind AIS G8 (Z701) EPIRB",
    "CSTA 289 Crewsaver Crewfind G8 (Z702) EPIRB",
    "CSTA 289 Crewsaver Crewfind E8 (Z704) non-GPS EPIRB"
  ],
  "Dowty": ["RN ECB Type 699(1) EPIRB"],
  "DRS": ["CSTA 121, BAU 35 / 35-A ELT"],
  "ELTA": [
    "CSTA 20, AO6 / SO6 ELT",
    "CSTA 131, ADT 406 AF/AP ELT",
    "CSTA 153, ADT 406 S ELT",
    "CSTA 291, ELiTe (AF) ELT",
    "CSTA 291, ELiTe (S) ELT"
  ],
  "Emergency Beacon Corp": [
    "CSTA 168, EBC406/AP/AF/APM/AFM, ELT",
    "CSTA 168, EBC406/APH/406AFH/406HM/APHM/AFHM, ELT"
  ],
  "GEC Marconi": ["CSTA 100, 639 SIU, EPIRB"],
  "General EPIRB (unknown)": ["General (unknown) oddcodings, EPIRB"],
  "Haotong (SH) Technology Co Ltd": ["CSTA 240, STB910, EPIRB"],
  "Honeywell": [
    "CSTA 232, Rescu 406AFN2-1X-6X, ELT",
    "CSTA 235 Rescu AP, Portables: 1X/6X, Fixed: AH ELT",
    "CSTA 236 Rescu SE2 ELT",
    "CSTA 235, Rescu 406SG ELT",
    "CSTA 88, Rescu 406 ELT",
    "CSTA 171, Rescu 406 AFN ELT",
    "CSTA 171, Rescu 406 SE ELT",
    "CSTA 124, Rescu 406 AF ELT"
  ],
  "IESM": [
    "CSTA 13, 22, KANNAD 406S EPIRB",
    "CSTA 40, 14, 7, 23, KANNAD 406F (TAC & non-TAC) EPIRB",
    "CSTA 35, KANNAD FH/PH/WH EPIRB",
    "CSTA 92, KANNAD 406M EPIRB",
    "CSTA 138, XS2 GPS PLB",
    "CSTA 180, Kannad XS3 GPS PLB"
  ],
  "IESM / KANNAD": [
    "CSTA 149, GPS PRO/SVW/SV EPIRB",
    "CSTA 151, Kannad PRO EPIRB",
    "CSTA 162, Auto GPS EPIRB",
    "CSTA 162, Auto non-GPS EPIRB"
  ],
  "Jotron": [
    "CSTA 1, TRON 30S (MBI) EPIRB",
    "CSTA 1, TRON 30S (FBI) EPIRB",
    "CSTA 1, TRON 30S (FB2) EPIRB",
    "CSTA 50, 30S Mark II MB3 EPIRB",
    "CSTA 50, 30S Mark II FB3 EPIRB",
    "CSTA 50, 30S Mark II FBM3 EPIRB",
    "MTI 32, CSTA 50, TRON 30S Mk II FB3 EPIRB",
    "MTI 35, CSTA 50, TRON 30S Mk II MB3 EPIRB",
    "CSTA 50, TRON 30S MK II FBH3 EPIRB",
    "MTI 43, CSTA 50, TRON 30S MK II MB3 EPIRB",
    "MTI 44, CSTA 50, TRON 30S MK II FB3 EPIRB",
    "MTI 45, CSTA 50, TRON 30S MK II FBH3 EPIRB",
    "MTI 46, CSTA 95, TRON 40S MB4 EPIRB",
    "MTI 47, CSTA 95, TRON 40S FB4 EPIRB",
    "MTI 48, CSTA 95, TRON FBH4 EPIRB",
    "CSTA 99, TRON 45S (non-TAC) EPIRB",
    "CSTA 98, TRON 45 SX (Serialised non-TAC) EPIRB",
    "MTI 60, CSTA 95, TRON 40S MB4 EPIRB",
    "MTI 61, CSTA 95, TRON 40S FB4 EPIRB",
    "MTI 62, CSTA 95, TRON 40S FBH4 EPIRB",
    "MTI 70, CSTA 95, TRON 40S MB4 EPIRB",
    "MTI 71, CSTA 95, TRON 40S FB4 EPIRB",
    "MTI 72, CSTA 95, TRON 40S FBH4 EPIRB",
    "MTI 73, CSTA 95, TRON 40S MB5 EPIRB",
    "MTI 74, CSTA 95, TRON 40S FB5 EPIRB",
    "MTI 75, CSTA 95, TRON 40(S) MB5 EPIRB",
    "MTI 76, CSTA 95, TRON 40(S) FB5 EPIRB",
    "MTI 76, CSTA 95, TRON 40(S) MB5 EPIRB",
    "MTI 78, CSTA 95, TRON 40(S) FB5 EPIRB",
    "CSTA 185, non-GPS, 40S MKII EPIRB",
    "CSTA 222, 60S non-GPS EPIRB",
    "CSTA 122, TRON 40S GPS EPIRB",
    "CSTA 95, Tron 40S non-GPS EPIRB",
    "CSTA 99, TRON 45S, TAC coded EPIRB",
    "CSTA 98, Tron 45SX  TAC coded EPIRB",
    "CSTA 185, Jotron 40S MKII GPS EPIRB",
    "CSTA 222, FB6 MMSI encoded EPIRB",
    "CSTA 222, 60S GPS EPIRB",
    "CSTA 155, S-VDR EPIRB",
    "CSTA 155, S-VDR Capsule EPIRB",
    "CSTA 185, 40VDR, SVDR EPIRB",
    "CSTA 318, Tron 40 VDR Float Free EPIRB"
  ],
  "JRC": ["CSTA 80, JQE - 3A / 3A-J EPIRB"],
  "Kannad": [
    "CSTA 105, AP/AF/AF-H/AP-H ELT",
    "CSTA 105, AS ELT",
    "CSTA 105, ATP ELT",
    "CSTA 167, 406AF/AF(ER) Compact ELT",
    "CSTA 42, 406 ATP ELT",
    "CSTA 91, 406 ATP / ATP-M ELT",
    "CSTA 41, FH/WH/PH, TAC coded EPIRB",
    "CSTA 39, 406S, TAC coded EPIRB",
    "CSTA 163, Kannad non-GPS EPIRB",
    "CSTA 163, Kannad GPS EPIRB",
    "CSTA 201, Kannad Safelink GPS EPIRB",
    "CSTA 204 Safelink SportPro, non-GPS EPIRB",
    "CSTA 204 Safelink SportPro+, GPS EPIRB",
    "CSTA 249, Safelink SportPro, non-GPS EPIRB",
    "CSTA 249, Safelink SportPro+, GPS EPIRB",
    "CSTA 285 Safelink SportPro, non-GPS EPIRB",
    "CSTA 285 Safelink SportPro+, GPS EPIRB",
    "CSTA 289 Kannad Safepro AIS (Z701) EPIRB",
    "CSTA 289 Kannad Safe Pro (Z702) EPIRB",
    "CSTA 289 Kannad Safe (Z704) non-GPS EPIRB",
    "CSTA 216, Kannad Safelink Pro GPS PLB",
    "CSTA 194, Kannad, Safelink Solo, non GPS (310-xxxx) PLB",
    "CSTA 200, Kannad GPS XS4 PLB",
    "CSTA 203, Kannad GPS XS4 PLB",
    "CSTA 184, Kannad XS-ER GPS PLB",
    "CSTA 194, Kannad non-GPS XS-4 PLB",
    "CSTA 194, Kannad GPS XS-4 PLB",
    "CSTA 184, Safelink Pro GPS PLB",
    "CSTA 203, Kannad SafeLink Solo GPS (310-xxxx) PLB",
    "CSTA 200, Kannad Safelink Solo (310-xxxx) PLB",
    "CSTA 217, Kannad XS-4 GPS PLB",
    "CSTA 217, Kannad Safelink Solo 310 GPS PLB",
    "CSTA 217, Kannad  XS-4 non-GPS PLB",
    "CSTA 217, Kannad Safelink Solo 310 non-GPS PLB",
    "CSTA 216, Kannad XS-ER GPS PLB",
    "CSTA 229, Safelink Solo 310- or 311-xxxx PLB",
    "CSTA 229 XS-4 GPS 110 AIRCRAFT PLB (110,111)",
    "CSTA 217 XS-4 GPS 110 AIRCRAFT PLB (110, 111)",
    "CSTA 229, XS-4 GPS PLB",
    "CSTA 203 XS-4 GPS 110 PLB (110, 111)",
    "CSTA 243 Safelink Solo 310- or 311-xxxx PLB",
    "CSTA 263, Safelink Solo 310, 311, Z422 Fastfind Ranger, PLB",
    "CSTA 281 Safelink Solo 310, 311, Z422 Fastfind Ranger, PLB",
    "CSTA 292 Safelink Solo 310, 311, Z422 Fastfind Ranger, PLB"
  ],
  "Kelvin Hughes": ["CSTA 165, SVDR-A16 EPIRB"],
  "Kinetic Technology Int'l": [
    "CSTA 221, SA1G EPIRB",
    "CSTA 290, SA3G EPIRB",
    "CSTA 312, SAG2G PLB",
    "CSTA 312, SAGGN PLB",
    "CSTA 255, SA2G PLB"
  ],
  "Kolgrim-Don Ltd": ["CSTA 161, Marlin-406 / 406 A2 EPIRB"],
  "Litton": [
    "CSTA 19, 948, EPIRB",
    "CSTA 29, 948 Class II, EPIRB",
    "CSTA 73, Litton 952, EPIRB"
  ],
  "Lokata": [
    "CSTA 12, 406 H(X) EPIRB",
    "CSTA 27, 406 H(Y) EPIRB",
    "CSTA 10, 406 P(X) EPIRB",
    "CSTA 54, 406 PF(X) EPIRB",
    "CSTA 26, 406 MY EPIRB",
    "CSTA 63, 406 MHY EPIRB",
    "CSTA 54, 406 (PF)Y EPIRB",
    "CSTA 25, 406 (P)Y EPIRB",
    "CSTA 75, 406 2M EPIRB",
    "CSTA 75, 406 2A EPIRB",
    "CSTA 75, 406 2AH EPIRB"
  ],
  "McMurdo": [
    "MTI 6, CSTA 2, RT 160M EPIRB",
    "CSTA 2, RB 406 EPIRB",
    "MTI 10, CSTA 2, RT 160M EPIRB",
    "CSTA 85, LDT 61A/62A/61 Mk II EPIRB",
    "MTI 52, CSTA 106, E3 / SOS Rescue EPIRB",
    "MTI 53, CSTA 106, E3 / SOS Rescue EPIRB",
    "MTI 63, CSTA 106, E3 / SOS RESCUE EPIRB",
    "MTI 64, CSTA 106, E3 / SOS RESCUE EPIRB",
    "MTI 66, CSTA 106, E3 / SOS RESCUE EPIRB",
    "MTI 67, CSTA 106, E3 / SOS RESCUE EPIRB",
    "MTI 68, CSTA 106, E3 / SOS RESCUE EPIRB",
    "MTI 69, CSTA 106, E3 / SOS RESCUE EPIRB",
    "MTI 81, CSTA 106, E3 / SOS RESCUE EPIRB",
    "MTI 82, CSTA 106, E3 / SOS RESCUE EPIRB",
    "MTI 83, CSTA 106, E3 / SOS RESCUE EPIRB",
    "MTI 84, CSTA 106, E3 / SOS RESCUE EPIRB",
    "CSTA 163, (200-xxx) G5 EPIRB",
    "CSTA 204, G5 (200-xxx) EPIRB",
    "CSTA 289, McMurdo Smartfind AIS G8 (Z701) EPIRB",
    "CSTA 119, G4 406 GPS EPIRB",
    "CSTA 163, (100-xxx) non-GPS E5 EPIRB",
    "CSTA 204, E5 non-GPS (100-xxx) EPIRB",
    "CSTA 289 McMurdo Smartfind G8 (Z702) EPIRB",
    "CSTA 289 McMurdo Smartfind E8 (Z704) non-GPS EPIRB",
    "CSTA 165, A16, C1, VR-3030, VR-3000S SVDR EPIRB",
    "CSTA 129, Fastfind Plus + GPS, TAC coded",
    "CSTA 184, GPS Fastfind MAX-G PLB ",
    "CSTA 194, Fastfind PLB 210 GPS",
    "CSTA 200, Fastfind 210 GPS PLB",
    "CSTA 203, Fastfind 210 GPS PLB",
    "CSTA 217, McMurdo, CSTA 217, Fastfind PLB210 GPS",
    "CSTA 129, (National coded, non-TAC) GPS PLB Fastfind+",
    "CSTA 129, (National coded, non-TAC) non-GPS, PLB Fastfind",
    "CSTA 129, TAC coded, Fastfind non-GPS PLB",
    "CSTA 184, non-GPS Fastfind MAX PLB, 810-xxxx",
    "CSTA 194, Fastfind 200 non-GPS PLB",
    "CSTA 200, Fastfind 200 non-GPS PLB",
    "CSTA 200, McMurdo Fastfind 200 non-GPS PLB",
    "CSTA 184, McMurdo, Safelink Pro GPS PLB",
    "CSTA 201, McMurdo, FF210 PLB",
    "CSTA 217, McMurdo Fastfind PLB200 non-GPS ",
    "CSTA 216, McMurdo, Safelink Pro GPS PLB",
    "CSTA 216 McMurdo MaxG PLB",
    "CSTA 217, McMurdo SafeLink Solo PLB",
    "CSTA 184, McMurdo XS-ER GPS PLB",
    "CSTA 229 (210-xxxx) PLB"
  ],
  "McMurdo (Graseby)": ["CSTA 70, RT260/260M EPIRB"],
  "McMurdo (Locat)": ["CSTA 53, LDT 61 EPIRB", "CSTA 53, LDT 62 EPIRB"],
  "Mobit Telecom Ltd": ["CSTA 238, SAT406 PLB"],
  "MPR/Alden Satfind": ["CSTA 71, PLB L2100"],
  "Navtec": ["CSTA 160, Global-C + EPIRB"],
  "NEW SUNRISE CO., LTD.": [
    "CSTA 253, NSR NEB-1000, HY-EP500, YZ-1000 EPIRB",
    "CSTA 262, NEB-2000C, HLD-FFC660, SLT-18C-FP1N EPIRB"
  ],
  "OCEAN SAFETY (ACR)": [
    "CSTA 258, 3Si Guardian EPIRB",
    "CSTA 320, 3Si Guardian EPIRB",
    "CSTA 276, 3Si Guardian PLB",
    "CSTA 271, 3Si Guardian PLB",
    "CSTA 294 3Si Guardian PLB",
    "CSTA 301 3Si Guardian PLB",
    "CSTA 287 3Si Guardian Buoyant PLB",
    "CSTA 305 3Si Guardian PLB"
  ],
  "Ocean Signal": [
    "CSTA 211, GPS SafeSea E100G EPIRB",
    "CSTA 256, EG100, EPIRB1",
    "CSTA 282, SafeSea E100G EPIRB",
    "CSTA 297, EPIRB1",
    "CSTA 322, EPIRB1 non-Float Free EPIRB",
    "CSTA 332, EPIRB1 & EPIRB1 Pro (Float Free / non-Float Free) EPIRB",
    "CSTA 211, non-GPS SafeSea E100 EPIRB",
    "CSTA 282, SafeSea E100 non-GPS EPIRB Class 2 EPIRB",
    "CSTA 322, EPIRB1 Pro, Float Free / non-Float Free EPIRB",
    "CSTA 260, rescueMe PLB1",
    "CSTA 283, rescueME PLB1",
    "CSTA 299, rescueMePLB1",
    "CSTA 310, rescueMe PLB1",
    "CSTA 321, rescueMe PLB1",
    "CSTA 333 rescueME PLB1",
    "CSTA 342, rescueME PLB1",
    "CSTA 239, rescueME PLB1",
    "CSTA 239, rescueME PLB2",
    "CSTA 260, rescueMe PLB2",
    "CSTA 283, rescueME PLB2"
  ],
  "Ocean Signal (ACR)": ["CSTA 284, 3Si Guardian EPIRB"],
  "Orolia": [
    "CSTA 163, A5 Smartfind (Manual Act) EPIRB",
    "CSTA 249, E5, non-GPS EPIRB",
    "CSTA 249, G5, GPS EPIRB",
    "CSTA 204, A5G Smartfind EPIRB",
    "CSTA 285 E5, non-GPS EPIRB",
    "CSTA 285 G5, GPS EPIRB",
    "CSTA 2001, Fastfind Return Link (Z450) Manual ELT",
    "CSTA 159, G2R ELT",
    "CSTA 214, AF/AP INTEGRA (AF-H/AP-H INTEGRA)/(ER) ELT",
    "CSTA 263, Fastfind 220, 211, XS4, Z421 PLB",
    "CSTA 263, Orolia Ranger (420-xxxx) PLB",
    "CSTA 281, Fastfind 220, 211, XS4, Z421 PLB",
    "CSTA 281, Fastfind PLB 200/201 ",
    "CSTA 281, Fastfind Ranger (420-xxxx) PLB",
    "CSTA 292 Fastfind Ranger (420-xxxx) PLB",
    "CSTA 292 Fastfind PLB 200/201",
    "CSTA 304, Safelink Solo, Z424 (424-xxx) PLB",
    "CSTA 304, Fastfind Ranger, Z424 (424-xxx) PLB",
    "CSTA 2001, Fastfind Return Link (Z450) PLB",
    "CSTA 3001, Fastfind Return Link (Z450) PLB",
    "CSTA 229, Fastfind Ranger, (420-xxxx) PLB",
    "CSTA 243, GPS 200/201 Ranger (420-xxxx) PLB",
    "CSTA 263, Fastfind PLB 200/201 PLB",
    "CSTA 292, Fastfind 220, 211, XS4, Z421 PLB",
    "CSTA 304, Fastfind 220, Z423 (423-xxx) PLB",
    "CSTA 229, Fastfind 220 (220-xxxx) PLB",
    "CSTA 217, Fastfind Ranger (420-xxxx) PLB",
    "CSTA 217, Fastfind 220 (220-xxxx) PLB",
    "CSTA 203, Fastfind Ranger (420-xxxx) PLB",
    "CSTA 203, Fastfind 220 (220-xxxx) PLB",
    "CSTA 214, AF/AP Integra (AF-H/AP-H Integra)(ER) PLB",
    "CSTA 217, Orolia, Ranger (420-xxxx) PLB",
    "CSTA 217, Orolia, (220-xxxx) PLB",
    "CSTA 243, Fastfind 220 (220-xxxx) PLB"
  ],
  "Raytheon": ["CSTA 21, JQE-2A EPIRB"],
  "Refer to UKMCC": ["Nat.Loc.s/ns: 4100 to 14201 PLB"],
  "Samyung": [
    "CSTA 195, GPS SEP-500, SEP-500V EPIRB",
    "CSTA 117, SEP 406 non-GPS EPIRB"
  ],
  "Saracom": ["CSTA 94, EB-10 EPIRB"],
  "Sartech": [
    "MTI 85, CSTA 139 (non-TAC) non-GPS GME MT400/401/402/403",
    "CSTA 186, GPS MT403/G/FF/FG EPIRB",
    "CSTA 186, MT403 non-GPS EPIRB",
    "MTI 1202, CSTA 139, non-GPS, TAC coded MT400/401/402/403 ",
    "CSTA 139, GPS MT400 to 403 EPIRB",
    "CSTA 176, GPS GME MT410 PLB",
    "CSTA 273, GPS GME MT410G PLB",
    "CSTA 302, GPS GME MT410G PLB",
    "CSTA 176, GME MT410 PLB non-GPS",
    "CSTA 176, non-GPS PLB"
  ],
  "SATLINK": ["CSTA 202, ELB100GPS EPIRB"],
  "Seimac Ltd": ["CSTA 148, SLB-1000 PLB"],
  "Signature Industries": [
    "CSTA 142, BE 369/406 EPIRB",
    "CSTA 706, BE586 G2R PLB",
    "CSTA 709, SARBE 6 PLB",
    "CSTA 712, AAPLB"
  ],
  "Simrad": [
    "CSTA 163, GPS EG50 EPIRB",
    "CSTA 163, non-GPS EP50 EPIRB",
    "CSTA 204, GPS EG50 EPIRB",
    "CSTA 204, non-GPS EP50 EPIRB",
    "CSTA 222, EP70, non-GPS EPIRB",
    "CSTA 222, EG70, GPS EPIRB",
    "CSTA 249, EP50, non-GPS EPIRB",
    "CSTA 249, EG50, GPS EPIRB",
    "CSTA 285 EP50, non-GPS EPIRB",
    "CSTA 285 EG50, GPS EPIRB"
  ],
  "Skanti": ["CSTA 77, TP2 I & II EPIRB"],
  "Standard Communications Pty Ltd": ["CSTA 300, MT603G EPIRB"],
  "Taiyo Musen Co Ltd": [
    "CSTA 164, Teb700 / JQE-103 EPIRB",
    "CSTA 164, GPS, Teb700/JQE-103 EPIRB"
  ],
  "Techtest": [
    "CSTA 103, ELT 503-12",
    "CSTA 223, 500-32 ELT / PLB",
    "CSTA 244, GPS/non-GPS, 503.16 & variants",
    "CSTA 93, 503-1 ELT",
    "CSTA 111 non-GPS 500-12 ELT",
    "CSTA 97, Techtest 503-1 ELT",
    "CSTA 111, GPS 500-27 ELT",
    "CSTA 111, non-GPS 500-12Y ELT",
    "CSTA 111, PLB GPS & non-GPS 500-27",
    "CSTA 111, PLB non-GPS 500-12 or 500-12Y",
    "CSTA 111, GPS 500-27 PELS",
    "CSTA 223, 500-32 PLB"
  ],
  "Thrane & Thrane": [
    "CSTA 163, Sailor non-GPS SEII EPIRB",
    "CSTA 163, Sailor SGEII, GPS EPIRB",
    "CSTA 204, non-GPS Sailor SEII EPIRB",
    "CSTA 204, GPS Sailor SGEII EPIRB",
    "CSTA 249, SEII, non-GPS EPIRB",
    "CSTA 249, SGEII, GPS EPIRB",
    "CSTA 285 SEII, non-GPS EPIRB",
    "CSTA 285 SGEII, GPS EPIRB",
    "CSTA 289, Thrane & Thrane, (702) 4065 GNSS EPIRB"
  ],
  "Ultra Electronics Ocean Systems": ["CSTA 718, T-1630/SRT Buoy EPIRB"],
  "UNKNOWN": [
    "EPIRB awaiting information",
    "EPIRB Corrupted Hex Ids",
    "SSAS Corrupted Hex Ids",
    "SSAS awaiting information",
    "SVDR awaiting information",
    "MMSI coded, non-GPS, model not indicated",
    "MMSI coded, GPS, model not indicated",
    "SSAS, GPS, model not indicated",
    "SVDR, GPS, MMSI, model indicated",
    "SVDR Corrupted Hex Ids",
    "EPIRB Test coded",
    "SSAS Test coded",
    "SVDR Test coded",
    "Orbitography beacon",
    "ELT awaiting information",
    "ELT Corrupted Hex Ids",
    "ELT, model unknown, non-GPS, 24-bit address",
    "ELT, model unknown, GPS, 24-bit address",
    "ELT, model unknown, non-GPS, Aircraft Mark",
    "ELT, model unknown, GPS, Aircraft Mark",
    "ELT, model unknown, non-GPS, AOD + sn",
    "ELT, model unknown, GPS, AOD + sn",
    "ELT Test coded",
    "non-specific ELT, model unknown",
    "PLB Test coded",
    "PLB awaiting information",
    "PLB Corrupted Hex Ids",
    "Unkown Corrupted Hex Ids"
  ]
}
